t_rex/__init__.py
t_rex/completer.py
t_rex/executor.py
t_rex/keybindings.py
t_rex/layout.py
t_rex/main.py
t_rex/postprocessors.py
t_rex/result_processors.py
t_rex/packages/__init__.py
t_rex/packages/completion_engine.py
t_rex-0.0.10.dist-info/METADATA
t_rex-0.0.10.dist-info/WHEEL
t_rex-0.0.10.dist-info/entry_points.txt
t_rex-0.0.10.dist-info/top_level.txt
t_rex-0.0.10.dist-info/RECORD
